{
  "seo": {
    "title": "Try It now",
    "description": "Step by step instructions for installing the YakShaver browser extension and using it",
    "openGraphTitle": "Try It now",
    "openGraphDescription": "Step by step instructions for installing the YakShaver browser extension and using it"
  },
  "title": "fad",
  "pageBlocks": [
    {
      "topImage": {
        "imgSrc": "/YakShaver/YakShaver Darkmode.png",
        "imgWidth": 514,
        "imgHeight": 104
      },
      "tryItNowTitle": "Start recording in 3 easy steps!",
      "tryItNowCards": [
        {
          "title": "1. Pin extension",
          "description": "Click the ![](/TryItNow/puzzle.svg) at the top right of your browser, then ![](/TryItNow/pin.svg) next to Screencastify.\n",
          "image": {
            "imgSrc": "/TryItNow/pin-yakshaver.png",
            "imgWidth": 480,
            "imgHeight": 336
          }
        },
        {
          "title": "2. Enable devices",
          "description": "Click the button below to set up your recording devices.\n",
          "button": {
            "label": "![](/TryItNow/microphone.svg)Enable Mic & Webcam\n"
          }
        },
        {
          "title": "3. Pin extension",
          "description": "Click the  at the top right of your browser, then the  next to Screencastify.\n",
          "image": {
            "imgSrc": "/TryItNow/yaskhaver-this-tab.png",
            "imgWidth": 480,
            "imgHeight": 336
          }
        }
      ],
      "bottomLinks": [
        {
          "label": "![](/TryItNow/question.svg)Learn More\n"
        },
        {
          "label": "![](/TryItNow/camera.svg)Watch Video\n",
          "url": ""
        }
      ],
      "_template": "tryItNow"
    }
  ],
  "pageFormatting": {
    "bottomPadding": "small"
  }
}